api_24sea/__init__.py
api_24sea/abc.py
api_24sea/exceptions.py
api_24sea/singleton.py
api_24sea/utils.py
api_24sea/version.py
api_24sea/datasignals/__init__.py
api_24sea/datasignals/core.py
api_24sea/datasignals/fatigue.py
api_24sea/datasignals/schemas.py
api_24sea-2.1.6.dist-info/licenses/LICENSE
api_24sea-2.1.6.dist-info/WHEEL
api_24sea-2.1.6.dist-info/METADATA
api_24sea-2.1.6.dist-info/RECORD
