Metadata-Version: 2.4
Name: api-24sea
Version: 2.1.6
Summary: Facilitate the users' interaction with the 24SEA API (https://api/24sea/eu) by providing pandas interfaces to the API endpoints.
Author-email: Pietro D'Antuono <pietro.dantuono@24sea.eu>
Maintainer-email: Pietro D'Antuono <pietro.dantuono@24sea.eu>
Requires-Python: >=3.8.0,<3.14
Classifier: Development Status :: 4 - Beta
Classifier: Environment :: Console
Classifier: Intended Audience :: Science/Research
Classifier: Intended Audience :: Information Technology
Classifier: License :: OSI Approved :: GNU General Public License v3 (GPLv3)
Classifier: Natural Language :: English
Classifier: Operating System :: POSIX :: Linux
Classifier: Programming Language :: Python :: 3
Classifier: Programming Language :: Python :: 3.8
Classifier: Programming Language :: Python :: 3.9
Classifier: Programming Language :: Python :: 3.10
Classifier: Programming Language :: Python :: 3.11
Classifier: Programming Language :: Python :: 3.12
Classifier: Programming Language :: Python :: 3.13
Classifier: Topic :: Database
License-File: LICENSE
Requires-Dist: pandas
Requires-Dist: pydantic
Requires-Dist: shorthand_datetime>=0.2.1,<1.0.0
Requires-Dist: httpx>=0.28.0,<1.0.0
Requires-Dist: tqdm>=4.65.0,<5.0.0
Requires-Dist: api-24sea-ai>=0.1.0 ; extra == "ai"
Requires-Dist: py-fatigue>=2.0.0 ; extra == "fatigue" and ( python_version>='3.10')
Requires-Dist: py-fatigue>=1.0.0,<2.0.0 ; extra == "fatigue" and ( python_version<'3.10')
Requires-Dist: swifter>=1.4.0 ; extra == "fatigue"
Project-URL: 24SEA API Homepage, https://api.24SEA.eu/redoc/v1/
Project-URL: Documentation, https://api24seapydocs.z6.web.core.windows.net/
Project-URL: Homepage, https://24SEA.eu
Project-URL: Repository, https://bitbucket.org/24sea/api-24sea-pkg
Provides-Extra: ai
Provides-Extra: fatigue
